bake/__init__.py
bake/bake_cli.py
bake/core.py
bakery_build-1.0.4.dist-info/METADATA
bakery_build-1.0.4.dist-info/WHEEL
bakery_build-1.0.4.dist-info/entry_points.txt
bakery_build-1.0.4.dist-info/top_level.txt
bakery_build-1.0.4.dist-info/RECORD
