Metadata-Version: 2.4
Name: bakery-build
Version: 1.0.4
Summary: a simple build automation library and CLI tool
Author: Bradley Hutchings
Author-email: Bradley Hutchings <bkhnapa@gmail.com>
Classifier: Programming Language :: Python :: 3
Classifier: Development Status :: 2 - Pre-Alpha
Requires-Python: >=3.10
Dynamic: author
Dynamic: requires-python
